Metadata-Version: 1.2
Name: gnd-distributions
Version: 0.1
Summary: Gaussian and Binomial distribution
Home-page: UNKNOWN
Author: Areej Fatima
Author-email: areejch79@gmail.com
License: UNKNOWN
Platform: UNKNOWN
Classifier: Programming Language :: Python :: 3
Classifier: License :: OSI Approved :: MIT License
Classifier: Operating System :: OS Independent
Requires-Python: >=3.6
